Metadata-Version: 2.1
Name: TranslatorX
Version: 1.2
Summary: A Python package for translation that uses Google translator and also supports asynchronous programming!
Home-page: https://github.com/shayanheidari01/TranslatorX
Author: Shayan Heidari
Author-email: contact@shayanheidari.info
Keywords: translator,translate,google,asyncio,googletrans
Classifier: Programming Language :: Python :: 3.7
Classifier: Programming Language :: Python :: 3.8
Classifier: Programming Language :: Python :: 3.9
Classifier: Programming Language :: Python :: 3.10
Classifier: Programming Language :: Python :: 3.11
Classifier: Programming Language :: Python :: 3.12
Classifier: License :: OSI Approved :: GNU Lesser General Public License v3 (LGPLv3)
Requires-Python: ~=3.7
